tyl_tools.py
tyl_tools-1.0.dist-info/METADATA
tyl_tools-1.0.dist-info/WHEEL
tyl_tools-1.0.dist-info/top_level.txt
tyl_tools-1.0.dist-info/RECORD
