Metadata-Version: 2.1
Name: tyl_tools
Version: 1.0
Summary: A  module for test
Author: tyl
Author-email: 2371527712@qq.com
License: MIT
